google/cloud/audit/__init__.py
google/cloud/audit/audit_log.proto
google/cloud/audit/audit_log_pb2.py
google/cloud/audit/bigquery_audit_metadata.proto
google/cloud/audit/bigquery_audit_metadata_pb2.py
google_cloud_audit_log-0.3.0.dist-info/LICENSE
google_cloud_audit_log-0.3.0.dist-info/METADATA
google_cloud_audit_log-0.3.0.dist-info/WHEEL
google_cloud_audit_log-0.3.0.dist-info/top_level.txt
google_cloud_audit_log-0.3.0.dist-info/RECORD
