Metadata-Version: 2.1
Name: google-cloud-audit-log
Version: 0.3.0
Summary: Google Cloud Audit Protos
Home-page: https://github.com/googleapis/python-audit-log
Author: Google LLC
Author-email: googleapis-packages@google.com
License: Apache-2.0
Classifier: Development Status :: 4 - Beta
Classifier: Intended Audience :: Developers
Classifier: License :: OSI Approved :: Apache Software License
Classifier: Programming Language :: Python
Classifier: Programming Language :: Python :: 3
Classifier: Programming Language :: Python :: 3.7
Classifier: Programming Language :: Python :: 3.8
Classifier: Programming Language :: Python :: 3.9
Classifier: Programming Language :: Python :: 3.10
Classifier: Programming Language :: Python :: 3.11
Classifier: Programming Language :: Python :: 3.12
Classifier: Programming Language :: Python :: Implementation :: CPython
Requires-Python: >=3.7
License-File: LICENSE
Requires-Dist: protobuf!=4.21.1,!=4.21.2,!=4.21.3,!=4.21.4,!=4.21.5,<6.0.0dev,>=3.20.2
Requires-Dist: googleapis-common-protos<2.0dev,>=1.56.2
